monk/errors.py
monk/__init__.py
monk/compat.py
monk/helpers.py
monk/mongo.py
monk/modeling.py
monk/schema.py
monk/validators.py
monk/validation.py
monk/manipulation.py
monk/shortcuts.py
monk-0.14.0_dev.dist-info/metadata.json
monk-0.14.0_dev.dist-info/METADATA
monk-0.14.0_dev.dist-info/top_level.txt
monk-0.14.0_dev.dist-info/RECORD
monk-0.14.0_dev.dist-info/DESCRIPTION.rst
monk-0.14.0_dev.dist-info/WHEEL
