Metadata-Version: 2.0
Name: monk
Version: 0.14.0-dev
Summary: An unobtrusive data modeling, manipulation and validation library. MongoDB included.
Home-page: http://github.com/neithere/monk/
Author: Andrey Mikhaylenko
Author-email: neithere@gmail.com
License: GNU Lesser General Public License (LGPL), Version 3
Keywords: mongo mongodb document query database api model models orm odm document-oriented non-relational nosql validation filling
Platform: UNKNOWN
Classifier: Development Status :: 4 - Beta
Classifier: Intended Audience :: Developers
Classifier: Intended Audience :: Information Technology
Classifier: License :: OSI Approved :: GNU Library or Lesser General Public License (LGPL)
Classifier: Programming Language :: Python
Classifier: Programming Language :: Python :: 2
Classifier: Programming Language :: Python :: 2.6
Classifier: Programming Language :: Python :: 2.7
Classifier: Programming Language :: Python :: 3
Classifier: Programming Language :: Python :: 3.2
Classifier: Programming Language :: Python :: 3.3
Classifier: Programming Language :: Python :: Implementation :: CPython
Classifier: Programming Language :: Python :: Implementation :: PyPy
Classifier: Topic :: Database :: Front-Ends
Classifier: Topic :: Software Development :: Libraries
Classifier: Topic :: Software Development :: Libraries :: Python Modules
Requires: python (>= 2.6)
Provides: monk
